pyghthouse/__init__.py
pyghthouse/ph.py
pyghthouse/connection/__init__.py
pyghthouse/connection/wsconnector.py
pyghthouse/data/__init__.py
pyghthouse/data/canvas.py
pyghthouse/utils/__init__.py
pyghthouse/utils/_color.py
pyghthouse-0.2.0.dist-info/LICENSE
pyghthouse-0.2.0.dist-info/METADATA
pyghthouse-0.2.0.dist-info/WHEEL
pyghthouse-0.2.0.dist-info/top_level.txt
pyghthouse-0.2.0.dist-info/RECORD
