Metadata-Version: 2.1
Name: pyghthouse
Version: 0.2.0
Summary: Python Lighthouse adapter
Home-page: https://github.com/Musicted/pyghthouse
Author: Gavin Lüdemann
Author-email: gavin.luedemann@gmail.com
License: MIT
Platform: UNKNOWN
Requires-Python: >=3.8
License-File: LICENSE
Requires-Dist: numpy (~=1.21.2)
Requires-Dist: websocket-client (~=1.2.1)
Requires-Dist: msgpack (~=1.0.2)
